{"cameraMode":{"drawMode":0,"name":"Shaded","section":"Shading Mode"},"sceneLighting":true,"audioPlay":false,"sceneViewState":{"showFog":true,"showMaterialUpdate":false,"showSkybox":true,"showFlares":true,"showImageEffects":true,"showParticleSystems":true,"showVisualEffectGraphs":true,"m_FxEnabled":true},"in2DMode":false,"pivot":{"x":-19.350234985351564,"y":19.72647476196289,"z":3.384352207183838},"rotation":{"x":-0.0727398470044136,"y":0.9120309352874756,"z":-0.35899287462234499,"w":-0.18471087515354157},"size":12.12435531616211,"orthographic":false}